<?xml version="1.0" encoding="utf-8"?>
<toggles>
	<toggle id="1">
		<name>Aspect de l'idole</name>
		<effect>Utilisé pour changer l'aspect de votre statue.</effect>
		<desc>Ce sélecteur permet à la statue de prendre d'autres apparences, comme la pierre, l'or, le biscuit, ou même celles de vos filles.</desc>
		<quote></quote>
		<options>
			<option id="10">
				<name>Aspect d'Argile</name>
				<desc>Son apparence originelle.</desc>
				<quote></quote>
			</option>
			<option id="11">
				<name>Aspect de Paille</name>
				<desc>Apparence simple imitant un épouvantail.</desc>
				<quote></quote>
			</option>
			<option id="111">
				<name>Aspect de Fermière</name>
				<desc></desc>
				<quote></quote>
			</option>
			<option id="112">
				<name>Aspect de Trayeuse</name>
				<desc></desc>
				<quote></quote>
			</option>
			<option id="113">
				<name>Aspect d'Ouvrière</name>
				<desc></desc>
				<quote></quote>
			</option>
			<option id="121">
				<name>Aspect de Soubrette</name>
				<desc></desc>
				<quote></quote>
			</option>
			<option id="122">
				<name>Aspect de Vétérinaire</name>
				<desc></desc>
				<quote></quote>
			</option>
			<option id="123">
				<name>Aspect de Scientifique</name>
				<desc></desc>
				<quote></quote>
			</option>
			<option id="124">
				<name>Aspect de Scientifique folle</name>
				<desc></desc>
				<quote></quote>
			</option>
			<option id="125">
				<name>Aspect de Spationaute</name>
				<desc></desc>
				<quote></quote>
			</option>
			<option id="126">
				<name>Aspect de Scientifique maléfique</name>
				<desc></desc>
				<quote></quote>
			</option>
			<option id="131">
				<name>Aspect d'Hôtesse</name>
				<desc></desc>
				<quote></quote>
			</option>
			<option id="132">
				<name>Aspect de Prêtresse</name>
				<desc></desc>
				<quote></quote>
			</option>
			<option id="133">
				<name>Aspect d'Alchimiste</name>
				<desc></desc>
				<quote></quote>
			</option>
			<option id="134">
				<name>Aspect de Sorcière</name>
				<desc></desc>
				<quote></quote>
			</option>
			<option id="135">
				<name>Aspect d'Arpenteuse de plan</name>
				<desc></desc>
				<quote></quote>
			</option>
			<option id="136">
				<name>Aspect de Déesse</name>
				<desc></desc>
				<quote></quote>
			</option>
			<option id="144">
				<name>Aspect d'Esclavagiste</name>
				<desc></desc>
				<quote></quote>
			</option>
			<option id="211">
				<name>Aspect de Mendiante</name>
				<desc></desc>
				<quote></quote>
			</option>
			<option id="212">
				<name>Aspect d'Esclave asiatique</name>
				<desc></desc>
				<quote></quote>
			</option>
			<option id="222">
				<name>Aspect d'Esclave russe</name>
				<desc></desc>
				<quote></quote>
			</option>
			<option id="223">
				<name>Aspect d'Esclave mutante</name>
				<desc></desc>
				<quote></quote>
			</option>
			<option id="224">
				<name>Aspect de Fille alien</name>
				<desc></desc>
				<quote></quote>
			</option>
			<option id="225">
				<name>Aspect d'Esclave ESPer</name>
				<desc></desc>
				<quote></quote>
			</option>
			<option id="226">
				<name>Aspect de Succube</name>
				<desc></desc>
				<quote></quote>
			</option>
			<option id="232">
				<name>Aspect d'Esclave arabe</name>
				<desc></desc>
				<quote></quote>
			</option>
			<option id="233">
				<name>Aspect d'Esclave familière</name>
				<desc></desc>
				<quote></quote>
			</option>
			<option id="234">
				<name>Aspect d'Esclave elfe</name>
				<desc></desc>
				<quote></quote>
			</option>
			<option id="235">
				<name>Aspect de Fille goule</name>
				<desc></desc>
				<quote></quote>
			</option>
			<option id="236">
				<name>Aspect de Séraphin</name>
				<desc></desc>
				<quote></quote>
			</option>
			<option id="242">
				<name>Aspect de Fille brebis</name>
				<desc></desc>
				<quote></quote>
			</option>
			<option id="243">
				<name>Aspect de Fille chèvre</name>
				<desc></desc>
				<quote></quote>
			</option>
			<option id="244">
				<name>Aspect de Fille jument</name>
				<desc></desc>
				<quote></quote>
			</option>
			<option id="245">
				<name>Aspect de Fille vache</name>
				<desc></desc>
				<quote></quote>
			</option>
			<option id="251">
				<name>Aspect de Fille lapine</name>
				<desc></desc>
				<quote></quote>
			</option>
			<option id="252">
				<name>Aspect de Fille truie</name>
				<desc></desc>
				<quote></quote>
			</option>
			<option id="253">
				<name>Aspect de Fille ourse</name>
				<desc></desc>
				<quote></quote>
			</option>
			<option id="254">
				<name>Aspect de Fille orque</name>
				<desc></desc>
				<quote></quote>
			</option>
			<option id="261">
				<name>Aspect de Fille chatte</name>
				<desc></desc>
				<quote></quote>
			</option>
			<option id="262">
				<name>Aspect de Fille louve</name>
				<desc></desc>
				<quote></quote>
			</option>
			<option id="263">
				<name>Aspect de Fille renne</name>
				<desc></desc>
				<quote></quote>
			</option>
			<option id="264">
				<name>Aspect de Fille chamelle</name>
				<desc></desc>
				<quote></quote>
			</option>
		</options>
	</toggle>
	<toggle id="300">
		<name>Contrôleur d'événements</name>
		<effect>Utilisé pour démarrer des événements.</effect>
		<desc>Ce sélecteur permet à la statue de jouer avec le temps, en invoquant des événements à volonté.</desc>
		<quote></quote>
		<options>
			<option id="301">
				<name>Temps normal</name>
				<desc>Laisse passer le temps normalement, les événements viendront de toute façon.</desc>
				<quote></quote>
			</option>
			<option id="302">
				<name>Imbolc</name>
				<desc></desc>
				<quote></quote>
			</option>
			<option id="303">
				<name>Ostara</name>
				<desc></desc>
				<quote></quote>
			</option>
			<option id="304">
				<name>Beltaine</name>
				<desc></desc>
				<quote></quote>
			</option>
			<option id="305">
				<name>Litha</name>
				<desc></desc>
				<quote></quote>
			</option>
			<option id="306">
				<name>Lugnasad</name>
				<desc></desc>
				<quote></quote>
			</option>
			<option id="307">
				<name>Mabon</name>
				<desc></desc>
				<quote></quote>
			</option>
			<option id="308">
				<name>Samain</name>
				<desc></desc>
				<quote></quote>
			</option>
			<option id="309">
				<name>Yule</name>
				<desc></desc>
				<quote></quote>
			</option>
		</options>
	</toggle>
	<toggle id="500">
		<name>Trayeuse</name>
		<effect>Sélectionner le mode de traite.</effect>
		<desc>Ce sélecteur vous permet de choisir la façon de traire le bétail.</desc>
		<quote></quote>
		<options>
			<option id="510">
				<name>Traite manuel</name>
				<desc>Le bétail est trait directement par les trayeuses (humaines...).</desc>
				<quote></quote>
				<Levels>
					<Level id="511">
						<name>Main de noob</name>
						<desc>Le bétail trait par une stagiaire fournit un lait faible, tant en qualité qu'en quantité</desc>
						<quote></quote>
					</Level>
					<Level id="512">
						<name>Main</name>
						<desc>Le bétail trait par une apprentie fournit un lait un peu faible mais c'est toujours mieux qu'une stagiaire.</desc>
						<quote></quote>
					</Level>
					<Level id="513">
						<name>Main expérimentée</name>
						<desc>Le bétail trait par une traiyeuse fournit un lait acceptable, tant en qualité qu'en quantité.</desc>
						<quote></quote>
					</Level>
					<Level id="514">
						<name>Main professionnelle</name>
						<desc>Le bétail trait par une traiyeuse experte fournit un bon lait, en qualité et en quantité.</desc>
						<quote></quote>
					</Level>
					<Level id="515">
						<name>Main de maître</name>
						<desc>Le bétail trait par une maîtresse traiyeuse fournit un très bon lait, en qualité et en quantité.</desc>
						<quote></quote>
					</Level>
					<Level id="516">
						<name>Main du Diable</name>
						<desc>Cette main démoniaque sait exactement comment faire plaisir au bétail pour obtenir un lait d'un goût excellent.</desc>
						<quote></quote>
					</Level>
					<Level id="517">
						<name>Main de Dieu</name>
						<desc>Le bétail trait par cette main céleste fournit du lait divin, en qualité et en quantité.</desc>
						<quote></quote>
					</Level>
				</Levels>
			</option>
			<option id="520">
				<name>Traite par machine</name>
				<desc>Le bétail est trait à l'aide de machine.</desc>
				<quote></quote>
				<Levels>
					<Level id="522">
						<name>Outil de traite</name>
						<desc>Un outils basique fait pour faciliter le travail des traiyeuses.</desc>
						<quote></quote>
					</Level>
					<Level id="523">
						<name>Machine de traite</name>
						<desc>Une machine créée pour augmenter la production de lait.</desc>
						<quote></quote>
					</Level>
					<Level id="524">
						<name>Machine médical</name>
						<desc>Une machine créée pour réduire le stress du bétail.</desc>
						<quote></quote>
					</Level>
					<Level id="525">
						<name>Machine jouissive</name>
						<desc>Une machine créée pour rendre la traite plus agréable pour le bétail.</desc>
						<quote></quote>
					</Level>
					<Level id="526">
						<name>Machine alien</name>
						<desc>Le bétail trait par cette machine fournit un lait excellent, en qualité et en quantité.</desc>
						<quote></quote>
					</Level>
					<Level id="527">
						<name>Machine ultime</name>
						<desc>La meilleure machine créée par l'esprit humain, rien ne peut battre cette quantité.</desc>
						<quote></quote>
					</Level>
				</Levels>
			</option>
			<option id="530">
				<name>Traite par tentacule</name>
				<desc>Le bétail est trait par des créatures organiques appelée tentacules.</desc>
				<quote></quote>
				<Levels>
					<Level id="532">
						<name>Trayeuse organique</name>
						<desc>Un organisme créé pour rendre la traite plus naturelle pour le bétail.</desc>
						<quote></quote>
					</Level>
					<Level id="533">
						<name>Trayeuse vivante</name>
						<desc>Une chose vivante créée pour simuler un bébé bétail.</desc>
						<quote></quote>
					</Level>
					<Level id="534">
						<name>Jeune tentacule</name>
						<desc>Un petit tentacule avec un appétit vorace.</desc>
						<quote></quote>
					</Level>
					<Level id="535">
						<name>Tentacule</name>
						<desc>Les tentacules sont des créatures ressemblant aux vers, qui aiment le lait plus que tout.</desc>
						<quote></quote>
					</Level>
					<Level id="536">
						<name>Tentacule ancienne</name>
						<desc>Un énorme tentacule favorisant la quantité par rapport à la qualité.</desc>
						<quote></quote>
					</Level>
					<Level id="537">
						<name>Reine tentacule</name>
						<desc>Reine de son espèce, elle produit le lait avec le meilleur goût.</desc>
						<quote></quote>
					</Level>
				</Levels>
			</option>
		</options>
	</toggle>
</toggles>